latex_generator/__init__.py
latex_generator/latex_generator.py
newawersometexcellentwondertexdragonphoenixninjaunicorntexasrangerlatexmasterpiecegenerator-0.1.0.dist-info/licenses/LICENSE
newawersometexcellentwondertexdragonphoenixninjaunicorntexasrangerlatexmasterpiecegenerator-0.1.0.dist-info/METADATA
newawersometexcellentwondertexdragonphoenixninjaunicorntexasrangerlatexmasterpiecegenerator-0.1.0.dist-info/WHEEL
newawersometexcellentwondertexdragonphoenixninjaunicorntexasrangerlatexmasterpiecegenerator-0.1.0.dist-info/top_level.txt
newawersometexcellentwondertexdragonphoenixninjaunicorntexasrangerlatexmasterpiecegenerator-0.1.0.dist-info/RECORD
